README.rst
setup.py
extend_Library/__init__.py
extend_Library/extend_Library.py
extend_Library.egg-info/PKG-INFO
extend_Library.egg-info/SOURCES.txt
extend_Library.egg-info/dependency_links.txt
extend_Library.egg-info/requires.txt
extend_Library.egg-info/top_level.txt