Metadata-Version: 1.1
Name: extend-Library
Version: 1.0.0
Summary: Extend library for EMP.
Home-page: https://github.com/desion/tidy_page
Author: SRTest
Author-email: liuhy@emrubik.com
License: MIT
Platform: UNKNOWN
Classifier: Environment :: Web Environment
Classifier: Intended Audience :: Developers
Classifier: Operating System :: OS Independent
Classifier: Topic :: Text Processing :: Indexing
Classifier: Topic :: Utilities
Classifier: Topic :: Internet
Classifier: Topic :: Software Development :: Libraries :: Python Modules
Classifier: Programming Language :: Python
Classifier: Programming Language :: Python :: 2
Classifier: Programming Language :: Python :: 2.6
Classifier: Programming Language :: Python :: 2.7
